nliwasa/__init__.py
nliwasa/details.py
nliwasa/skills.py
nliwasa-0.1.0.dist-info/METADATA
nliwasa-0.1.0.dist-info/WHEEL
nliwasa-0.1.0.dist-info/RECORD
